CigarIterator/__init__.py
CigarIterator-1.0.3.dist-info/DESCRIPTION.rst
CigarIterator-1.0.3.dist-info/METADATA
CigarIterator-1.0.3.dist-info/RECORD
CigarIterator-1.0.3.dist-info/WHEEL
CigarIterator-1.0.3.dist-info/metadata.json
CigarIterator-1.0.3.dist-info/top_level.txt
